cdk_validator_checkov/__init__.py
cdk_validator_checkov/py.typed
cdk_validator_checkov/_jsii/__init__.py
cdk_validator_checkov/_jsii/cdk-validator-checkov@0.0.2.jsii.tgz
cdk_validator_checkov-0.0.2.dist-info/LICENSE
cdk_validator_checkov-0.0.2.dist-info/METADATA
cdk_validator_checkov-0.0.2.dist-info/WHEEL
cdk_validator_checkov-0.0.2.dist-info/top_level.txt
cdk_validator_checkov-0.0.2.dist-info/RECORD
